ASIS/__init__.py
ASIS/main.py
asisai-0.2.1a1.dist-info/LICENSE
asisai-0.2.1a1.dist-info/METADATA
asisai-0.2.1a1.dist-info/WHEEL
asisai-0.2.1a1.dist-info/top_level.txt
asisai-0.2.1a1.dist-info/RECORD
