Metadata-Version: 2.1
Name: asisai
Version: 0.2.1a1
Summary: UNKNOWN
Home-page: UNKNOWN
License: UNKNOWN
Platform: UNKNOWN
License-File: LICENSE
